MANIFEST.in
README.txt
licenceinfo.txt
plonetheme.bronzecube-configure.zcml
setup.cfg
setup.py
docs/HISTORY.txt
docs/INSTALL.txt
docs/LICENSE.GPL
docs/LICENSE.txt
plonetheme/__init__.py
plonetheme.bronzecube.egg-info/PKG-INFO
plonetheme.bronzecube.egg-info/SOURCES.txt
plonetheme.bronzecube.egg-info/dependency_links.txt
plonetheme.bronzecube.egg-info/entry_points.txt
plonetheme.bronzecube.egg-info/namespace_packages.txt
plonetheme.bronzecube.egg-info/not-zip-safe
plonetheme.bronzecube.egg-info/paster_plugins.txt
plonetheme.bronzecube.egg-info/requires.txt
plonetheme.bronzecube.egg-info/top_level.txt
plonetheme/bronzecube/__init__.py
plonetheme/bronzecube/configure.zcml
plonetheme/bronzecube/profiles.zcml
plonetheme/bronzecube/setuphandlers.py
plonetheme/bronzecube/skins.zcml
plonetheme/bronzecube/tests.py
plonetheme/bronzecube/version.txt
plonetheme/bronzecube/browser/__init__.py
plonetheme/bronzecube/browser/configure.zcml
plonetheme/bronzecube/browser/interfaces.py
plonetheme/bronzecube/browser/viewlet.pt
plonetheme/bronzecube/browser/viewlets.py
plonetheme/bronzecube/browser/images/README.txt
plonetheme/bronzecube/browser/images/blockheader.png
plonetheme/bronzecube/browser/images/header.jpg
plonetheme/bronzecube/browser/images/next_icon.gif
plonetheme/bronzecube/browser/images/search_icon.gif
plonetheme/bronzecube/browser/images/selected_menu_item_icon.gif
plonetheme/bronzecube/browser/portlets/__init__.py
plonetheme/bronzecube/browser/portlets/login.pt
plonetheme/bronzecube/browser/portlets/login.py
plonetheme/bronzecube/browser/portlets/news.pt
plonetheme/bronzecube/browser/portlets/news.py
plonetheme/bronzecube/browser/stylesheets/README.txt
plonetheme/bronzecube/browser/stylesheets/main.css
plonetheme/bronzecube/browser/templates/footer.pt
plonetheme/bronzecube/browser/templates/searchbox.pt
plonetheme/bronzecube/browser/templates/sections.pt
plonetheme/bronzecube/profiles/default/cssregistry.xml
plonetheme/bronzecube/profiles/default/jsregistry.xml
plonetheme/bronzecube/profiles/default/metadata.xml
plonetheme/bronzecube/profiles/default/plonetheme.bronzecube_various.txt
plonetheme/bronzecube/profiles/default/skins.xml
plonetheme/bronzecube/profiles/default/viewlets.xml
plonetheme/bronzecube/skins/plonetheme_bronzecube_bronzecube_styles
plonetheme/bronzecube/skins/plonetheme_bronzecube_custom_images/CONTENT.txt
