Metadata-Version: 1.0
Name: plonetheme.bronzecube
Version: 1.0
Summary: An installable theme for Plone 3
Home-page: http://svn.plone.org/svn/collective/
Author: Horacio Duran
Author-email: hduran@machinalis.com
License: GPL
Keywords: web zope plone theme
Platform: UNKNOWN
Classifier: Framework :: Plone
Classifier: Programming Language :: Python
